pursuitlib/__init__.py
pursuitlib/color.py
pursuitlib/decorators.py
pursuitlib/errors.py
pursuitlib/indexedenum.py
pursuitlib/iterators.py
pursuitlib/parsing.py
pursuitlib/utils.py
pursuitlib/console/__init__.py
pursuitlib/console/console.py
pursuitlib/console/table.py
pursuitlib/console/textcolor.py
pursuitlib/console/textcolors.py
pursuitlib/console/textcomponent.py
pursuitlib/console/textformatting.py
pursuitlib/console/textstyle.py
pursuitlib-0.4.0.dist-info/METADATA
pursuitlib-0.4.0.dist-info/WHEEL
pursuitlib-0.4.0.dist-info/top_level.txt
pursuitlib-0.4.0.dist-info/RECORD
