Metadata-Version: 2.1
Name: pursuitlib
Version: 0.4.0
Summary: Provides utility functions
Home-page: https://gitlab.com/frPursuit/pursuitlib-python
Author: Pursuit
Author-email: fr.pursuit@gmail.com
License: All rights reserved
Classifier: Programming Language :: Python :: 3
Classifier: Operating System :: OS Independent
Requires-Python: >=3.8
